polars_ls-0.5.4.dist-info/METADATA
polars_ls-0.5.4.dist-info/WHEEL
polars_ls-0.5.4.dist-info/entry_points.txt
pols/__init__.py
pols/cli.py
pols/features/S.py
pols/features/__init__.py
pols/features/common.py
pols/features/h_and_i.py
pols/features/hide.py
pols/features/l.py
pols/features/p.py
pols/features/v.py
pols/resegment.py
pols/walk.py
polars_ls-0.5.4.dist-info/RECORD
