Metadata-Version: 2.1
Name: polars-ls
Version: 0.5.4
Summary: List directory contents as Polars DataFrames
Author-Email: Louis Maddox <louismmx@gmail.com>
Project-URL: Homepage, https://github.com/lmmx/polars-ls
Project-URL: Repository, https://github.com/lmmx/polars-ls.git
Requires-Python: >=3.10
Requires-Dist: argh>=0.31.3
Provides-Extra: polars-lts-cpu
Requires-Dist: polars-lts-cpu>=1.21.0; extra == "polars-lts-cpu"
Provides-Extra: polars
Requires-Dist: polars>=1.21.0; extra == "polars"
Provides-Extra: dev
Requires-Dist: pdm>=2.22.3; extra == "dev"
Requires-Dist: pdm-bump>=0.9.10; extra == "dev"
